jsonstreams/__init__.py
jsonstreams/__init__.pyi
jsonstreams-0.5.0.dist-info/LICENSE
jsonstreams-0.5.0.dist-info/METADATA
jsonstreams-0.5.0.dist-info/WHEEL
jsonstreams-0.5.0.dist-info/top_level.txt
jsonstreams-0.5.0.dist-info/RECORD
