Metadata-Version: 2.1
Name: jsonstreams
Version: 0.5.0
Summary: A JSON streaming writer
Home-page: https://github.com/dcbaker/jsonstreams
Author: Dylan Baker
Author-email: dylan@pnwbakers.com
License: MIT
Keywords: JSON stream
Platform: UNKNOWN
Classifier: Development Status :: 4 - Beta
Classifier: License :: OSI Approved :: MIT License
Classifier: Programming Language :: Python :: 2
Classifier: Programming Language :: Python :: 2.7
Classifier: Programming Language :: Python :: 3
Classifier: Programming Language :: Python :: 3.5
Classifier: Programming Language :: Python :: 3.6
Classifier: Programming Language :: Python :: 3.7
Classifier: Programming Language :: Python :: 3.8
Classifier: Programming Language :: Python :: 3.9
Classifier: Intended Audience :: Developers
Requires-Python: >=2.7, !=3.0.*, !=3.1.*, !=3.2.*, !=3.3.*, !=3.4.*, !=3.5.*
Requires-Dist: six
Requires-Dist: enum34 ; python_version < "3.4"
Provides-Extra: recomended
Requires-Dist: simplejson ; extra == 'recomended'
Provides-Extra: test
Requires-Dist: tox ; extra == 'test'
